openai_function_calling/__init__.py
openai_function_calling/function.py
openai_function_calling/function_inferrer.py
openai_function_calling/helper_functions.py
openai_function_calling/json_schema_type.py
openai_function_calling/parameter.py
openai_function_calling/py.typed
openai_function_calling/tool_helpers.py
openai_function_calling-2.6.0.dist-info/METADATA
openai_function_calling-2.6.0.dist-info/WHEEL
openai_function_calling-2.6.0.dist-info/RECORD
