Metadata-Version: 2.1
Name: openai-function-calling
Version: 2.6.0
Summary: Helper functions to generate OpenAI GPT function calling requests.
Home-page: https://github.com/jakecyr/openai-function-calling
Author: Jake Cyr
Author-email: cyrjake@gmail.com
Requires-Python: >=3.9,<4.0
Classifier: Programming Language :: Python :: 3
Classifier: Programming Language :: Python :: 3.9
Classifier: Programming Language :: Python :: 3.10
Classifier: Programming Language :: Python :: 3.11
Classifier: Programming Language :: Python :: 3.12
Requires-Dist: docstring-parser (>=0.16,<0.17)
Requires-Dist: typing-extensions (>=4.12.2,<5.0.0)
Project-URL: Repository, https://github.com/jakecyr/openai-function-calling
